pytoon/__init__.py
pytoon/api.py
pytoon/cli.py
pytoon/core/__init__.py
pytoon/core/parser.py
pytoon/core/primitives.py
pytoon/core/scanner.py
pytoon/core/types.py
pytoon/core/writer.py
pytoon/decoding/__init__.py
pytoon/decoding/decoder.py
pytoon/decoding/normalize.py
pytoon/decoding/validation.py
pytoon/encoding/__init__.py
pytoon/encoding/encoder.py
pytoon/encoding/expand.py
pytoon/encoding/folding.py
pytoon/parser/__init__.py
pytoon/parser/parser.py
pytoon/parser/scanner.py
pytoon/utils/__init__.py
pytoon/utils/constants.py
pytoon/utils/literal_utils.py
pytoon/utils/string_utils.py
toonit-0.1.0.dist-info/licenses/LICENSE
toonit-0.1.0.dist-info/METADATA
toonit-0.1.0.dist-info/WHEEL
toonit-0.1.0.dist-info/entry_points.txt
toonit-0.1.0.dist-info/top_level.txt
toonit-0.1.0.dist-info/RECORD
