Metadata-Version: 2.4
Name: toonit
Version: 0.1.0
Summary: Python implementation of the TOON (Token-Oriented Object Notation) format
Author: Femi Alashi
License: MIT License
Project-URL: Homepage, https://github.com/femisimon/toonit
Requires-Python: >=3.8
License-File: LICENSE
Dynamic: license-file
